barfi/__init__.py
barfi/block_builder.py
barfi/compute_engine.py
barfi/option_builder.py
barfi/client/index.html
barfi/client/css/app.51aff32b.css
barfi/client/js/app.7f640bdf.js
barfi/client/js/app.7f640bdf.js.map
barfi/client/js/chunk-vendors.b25a8761.js
barfi/client/js/chunk-vendors.b25a8761.js.map
barfi/schema/__init__.py
barfi/schema/local_schema_manager.py
barfi/schema/preset.py
barfi/schema/schema_manager.py
tests/__init__.py
tests/debug.py
tests/demo.py
tests/test_app.py
tests/test_blocks.py
yoyobarfi-0.8.1.dist-info/LICENSE
yoyobarfi-0.8.1.dist-info/METADATA
yoyobarfi-0.8.1.dist-info/WHEEL
yoyobarfi-0.8.1.dist-info/top_level.txt
yoyobarfi-0.8.1.dist-info/RECORD
